satgpt/__init__.py
satgpt/make_role.py
satgpt/module_demo.py
satgpt/version.py
satgpt-0.0.4.dist-info/METADATA
satgpt-0.0.4.dist-info/WHEEL
satgpt-0.0.4.dist-info/top_level.txt
satgpt-0.0.4.dist-info/RECORD
