Metadata-Version: 2.1
Name: satgpt
Version: 0.0.4
Summary: GPT for satellite mission planning. In development. Get your API keys ready!
Author: Kevin Lalli
Author-email: kevin@opticsinspace.com
Requires-Dist: pystac
Requires-Dist: shell-gpt
